openclean/__init__.py
openclean/config.py
openclean/pipeline.py
openclean/version.py
openclean/cluster/__init__.py
openclean/cluster/base.py
openclean/cluster/index.py
openclean/cluster/key.py
openclean/cluster/knn.py
openclean/data/__init__.py
openclean/data/groupby.py
openclean/data/load.py
openclean/data/mapping.py
openclean/data/refdata.py
openclean/data/schema.py
openclean/data/sequence.py
openclean/data/serialize.py
openclean/data/types.py
openclean/data/util.py
openclean/data/archive/__init__.py
openclean/data/archive/base.py
openclean/data/archive/cache.py
openclean/data/archive/histore.py
openclean/data/metadata/__init__.py
openclean/data/metadata/base.py
openclean/data/metadata/fs.py
openclean/data/metadata/mem.py
openclean/data/source/__init__.py
openclean/data/source/socrata.py
openclean/data/store/__init__.py
openclean/data/store/base.py
openclean/data/store/fs.py
openclean/data/store/mem.py
openclean/data/stream/__init__.py
openclean/data/stream/base.py
openclean/data/stream/csv.py
openclean/data/stream/df.py
openclean/embedding/__init__.py
openclean/embedding/base.py
openclean/embedding/feature/__init__.py
openclean/embedding/feature/base.py
openclean/embedding/feature/character.py
openclean/embedding/feature/default.py
openclean/embedding/feature/frequency.py
openclean/embedding/feature/length.py
openclean/engine/__init__.py
openclean/engine/action.py
openclean/engine/base.py
openclean/engine/dataset.py
openclean/engine/library.py
openclean/engine/log.py
openclean/engine/operator.py
openclean/engine/parallel.py
openclean/engine/registry.py
openclean/engine/object/__init__.py
openclean/engine/object/base.py
openclean/engine/object/function.py
openclean/engine/object/mapping.py
openclean/engine/object/vocabulary.py
openclean/engine/store/__init__.py
openclean/engine/store/base.py
openclean/engine/store/default.py
openclean/engine/store/function.py
openclean/function/__init__.py
openclean/function/base.py
openclean/function/eval/__init__.py
openclean_core-0.4.1.dist-info/LICENSE
openclean_core-0.4.1.dist-info/METADATA
openclean_core-0.4.1.dist-info/WHEEL
openclean_core-0.4.1.dist-info/top_level.txt
openclean_core-0.4.1.dist-info/RECORD
