Metadata-Version: 2.1
Name: openclean-core
Version: 0.4.1
Summary: Library for data cleaning and data profiling
Home-page: https://github.com/VIDA-NYU/openclean
Author: Heiko Mueller
Author-email: heiko.muller@gmail.com
License: New BSD
Keywords: data cleaning
Platform: UNKNOWN
Classifier: License :: OSI Approved :: BSD License
Classifier: Operating System :: OS Independent
Classifier: Programming Language :: Python :: 3
Classifier: Programming Language :: Python :: 3.7
Classifier: Programming Language :: Python :: 3.8
Classifier: Programming Language :: Python :: 3.9
Classifier: Programming Language :: Python
Requires-Dist: future
Requires-Dist: appdirs (>=1.4.4)
Requires-Dist: python-dateutil
Requires-Dist: dill
Requires-Dist: requests
Requires-Dist: pandas (>=1.0.0)
Requires-Dist: scikit-learn
Requires-Dist: jsonschema (>=3.2.0)
Requires-Dist: histore (>=0.4.0)
Requires-Dist: flowserv-core (>=0.8.0)
Requires-Dist: jellyfish
Requires-Dist: refdata (>=0.2.0)
Requires-Dist: scipy
Provides-Extra: dev
Requires-Dist: flake8 ; extra == 'dev'
Requires-Dist: python-language-server ; extra == 'dev'
Requires-Dist: coverage (>=5.0) ; extra == 'dev'
Requires-Dist: pytest ; extra == 'dev'
Requires-Dist: pytest-cov ; extra == 'dev'
Provides-Extra: docs
Requires-Dist: Sphinx ; extra == 'docs'
Requires-Dist: sphinx-rtd-theme ; extra == 'docs'
Requires-Dist: sphinxcontrib-apidoc ; extra == 'docs'
Requires-Dist: jupyter-sphinx ; extra == 'docs'
Requires-Dist: nbsphinx ; extra == 'docs'
Requires-Dist: nbsphinx-link ; extra == 'docs'
Provides-Extra: tests
Requires-Dist: coverage (>=5.0) ; extra == 'tests'
Requires-Dist: pytest ; extra == 'tests'
Requires-Dist: pytest-cov ; extra == 'tests'
